{
  "project_info": {
    "project_number": "705430071504",
    "project_id": "gymmer-42987",
    "storage_bucket": "gymmer-42987.firebasestorage.app"
  },
  "client": [
    {
      "client_info": {
        "mobilesdk_app_id": "1:705430071504:android:9763ff894ce41e2d8cd6d5",
        "android_client_info": {
          "package_name": "com.m1x.gymmer"
        }
      },
      "oauth_client": [],
      "api_key": [
        {
          "current_key": "AIzaSyCN0Dm5tCONWyn_XZOLfgcoEY7xJGIVs-E"
        }
      ],
      "services": {
        "appinvite_service": {
          "other_platform_oauth_client": []
        }
      }
    }
  ],
  "configuration_version": "1"
}